torch_rc/__init__.py
torch_rc-0.4.1.dist-info/LICENSE
torch_rc-0.4.1.dist-info/METADATA
torch_rc-0.4.1.dist-info/WHEEL
torch_rc-0.4.1.dist-info/top_level.txt
torch_rc-0.4.1.dist-info/RECORD
