Metadata-Version: 2.1
Name: torch-rc
Version: 0.4.1
Summary: UNKNOWN
Home-page: UNKNOWN
License: UNKNOWN
Platform: UNKNOWN
Requires-Python: >=3.8
Requires-Dist: torch (>=1.8)
